videosdk/plugins/navana/__init__.py
videosdk/plugins/navana/stt.py
videosdk/plugins/navana/version.py
videosdk_plugins_navana-0.0.58.dist-info/METADATA
videosdk_plugins_navana-0.0.58.dist-info/WHEEL
videosdk_plugins_navana-0.0.58.dist-info/RECORD
