Metadata-Version: 2.4
Name: videosdk-plugins-navana
Version: 0.0.58
Summary: VideoSDK Agent Framework plugin for Navana STT services
Author: videosdk
License-Expression: Apache-2.0
Keywords: ai,audio,bodhi,indian-languages,navana,speech-to-text,stt,video,videosdk
Classifier: Development Status :: 4 - Beta
Classifier: Intended Audience :: Developers
Classifier: Topic :: Communications :: Conferencing
Classifier: Topic :: Multimedia :: Sound/Audio
Classifier: Topic :: Multimedia :: Video
Classifier: Topic :: Scientific/Engineering :: Artificial Intelligence
Requires-Python: >=3.11
Requires-Dist: aiohttp
Requires-Dist: bodhi-sdk
Requires-Dist: numpy
Requires-Dist: scipy>=1.11.0
Requires-Dist: videosdk-agents>=0.0.58
